[
  {
    "title": "Official Update: Regulatory Framework 2025-98",
    "url": "https://www.google.com/search?q=tr%20government%20Official%20Update%3A%20Regulatory%20Framework%202025-98",
    "date": "2026-02-08",
    "summary": "Public notification from the government of tr regarding regional updates and policy changes.",
    "status_level": "Notice",
    "collected_at": "2026-02-10T03:34:43.714890"
  },
  {
    "title": "Official Update: Regulatory Framework 2025-77",
    "url": "https://www.google.com/search?q=tr%20government%20Official%20Update%3A%20Regulatory%20Framework%202025-77",
    "date": "2026-02-05",
    "summary": "Public notification from the government of tr regarding regional updates and policy changes.",
    "status_level": "Critical",
    "collected_at": "2026-02-10T03:34:43.714885"
  }
]